[
  {
    "author": "Jan",
    "msgbox": "kokot zajebany",
    "timestamp": "12:34 12.5.1203"
  },
  {
    "author": "Hans",
    "msgbox": "což co karel",
    "timestamp": "18:55 5.10.5000"
  },
  {
    "author": "Ivan",
    "msgbox": "idk mneh",
    "timestamp": "8:12 15.8.2000"
  },
  {
    "author": "Jacek",
    "msgbox": "sleskyyyyy! xd lulw",
    "timestamp": "22:58 9.2.2055"
  },
  {
    "author": "sad",
    "msgbox": "asd",
    "timestamp": "21:46 2021.3.14"
  },
  {
    "author": "sadasd",
    "msgbox": "dsgsdfg",
    "timestamp": "21:47 2021.3.14"
  },
  {
    "author": "sadasd",
    "msgbox": "dsgsdfg",
    "timestamp": "21:47 2021.3.14"
  },
  {
    "author": "sadasd",
    "msgbox": "asdasd",
    "timestamp": "21:53 2021.3.14"
  },
  {
    "author": "sadasd",
    "msgbox": "asdasd",
    "timestamp": "21:54 2021.3.14"
  }
]